example/__init__.py
example/admin.py
example/app_settings.py
example/apps.py
example/auth_hooks.py
example/models.py
example/tasks.py
example/urls.py
example/views.py
example/locale/.gitkeep
example/migrations/0001_initial.py
example/migrations/__init__.py
example/static/example/.gitkeep
example/templates/example/base.html
example/templates/example/index.html
example/tests/__init__.py
example/tests/test_example.py
aa_example_plugin-0.0.8.dist-info/METADATA
aa_example_plugin-0.0.8.dist-info/WHEEL
aa_example_plugin-0.0.8.dist-info/licenses/LICENSE
aa_example_plugin-0.0.8.dist-info/RECORD
