Metadata-Version: 2.3
Name: aa-example-plugin
Version: 0.0.8
Summary: Example Plugin for Alliance Auth (GitHub Version)
Project-URL: Changelog, https://github.com/ppfeufer/aa-example-plugin/blob/master/CHANGELOG.md
Project-URL: Issue / Bug Reports, https://github.com/ppfeufer/aa-example-plugin/issues
Author-email: Peter Pfeufer <develop@ppfeufer.de>
License: GNU GENERAL PUBLIC LICENSE
License-File: LICENSE
Keywords: allianceauth,example
Classifier: Environment :: Web Environment
Classifier: Framework :: Django
Classifier: Framework :: Django :: 4.2
Classifier: Intended Audience :: Developers
Classifier: License :: OSI Approved :: GNU General Public License v3 (GPLv3)
Classifier: Operating System :: OS Independent
Classifier: Programming Language :: Python
Classifier: Programming Language :: Python :: 3 :: Only
Classifier: Programming Language :: Python :: 3.8
Classifier: Programming Language :: Python :: 3.9
Classifier: Programming Language :: Python :: 3.10
Classifier: Programming Language :: Python :: 3.11
Classifier: Programming Language :: Python :: 3.12
Classifier: Topic :: Internet :: WWW/HTTP
Classifier: Topic :: Internet :: WWW/HTTP :: Dynamic Content
Requires-Python: >=3.8
Requires-Dist: allianceauth<5.0.0,>=4
